{"_id":"component-builder","_rev":"146-6e2228bbcdbc2c299692dd27dc553e53","name":"component-builder","description":"builder for component","dist-tags":{"latest":"1.1.9"},"versions":{"0.0.1":{"name":"component-builder","version":"0.0.1","description":"Component build tool","keywords":["component","build"],"author":{"name":"TJ Holowaychuk","email":"tj@vision-media.caa"},"dependencies":{"batch":"0.1.1","component-require":"0.0.1","debug":"*"},"devDependencies":{"mocha":"*","should":"*"},"main":"index","_id":"component-builder@0.0.1","dist":{"shasum":"3d42b5690b57c2eb3189fef9f83feff2461f00cf","tarball":"http://registry.npmjs.org/component-builder/-/component-builder-0.0.1.tgz"},"maintainers":[{"name":"tjholowaychuk","email":"tj@vision-media.ca"}],"directories":{}},"0.0.2":{"name":"component-builder","version":"0.0.2","description":"Component build tool","keywords":["component","build"],"author":{"name":"TJ Holowaychuk","email":"tj@vision-media.caa"},"dependencies":{"batch":"0.1.1","component-require":"0.0.2","debug":"*"},"devDependencies":{"mocha":"*","should":"*"},"main":"index","_id":"component-builder@0.0.2","dist":{"shasum":"a96c3e0bba82e6327eb2605f8ada82f319d49234","tarball":"http://registry.npmjs.org/component-builder/-/component-builder-0.0.2.tgz"},"maintainers":[{"name":"tjholowaychuk","email":"tj@vision-media.ca"}],"directories":{}},"0.0.3":{"name":"component-builder","version":"0.0.3","description":"Component build tool","keywords":["component","build"],"author":{"name":"TJ Holowaychuk","email":"tj@vision-media.caa"},"dependencies":{"batch":"0.1.1","component-require":"0.0.2","debug":"*"},"devDependencies":{"mocha":"*","should":"*"},"main":"index","_id":"component-builder@0.0.3","dist":{"shasum":"0c297848f8e9472178a27f71e2bb6a42be464e0b","tarball":"http://registry.npmjs.org/component-builder/-/component-builder-0.0.3.tgz"},"maintainers":[{"name":"tjholowaychuk","email":"tj@vision-media.ca"}],"directories":{}},"0.0.4":{"name":"component-builder","version":"0.0.4","description":"Component build tool","keywords":["component","build"],"author":{"name":"TJ Holowaychuk","email":"tj@vision-media.caa"},"dependencies":{"batch":"0.1.1","component-require":"0.0.2","debug":"*"},"devDependencies":{"mocha":"*","should":"*"},"main":"index","_id":"component-builder@0.0.4","dist":{"shasum":"9e0b90a76fc24130da95192d08e9c500ced53960","tarball":"http://registry.npmjs.org/component-builder/-/component-builder-0.0.4.tgz"},"maintainers":[{"name":"tjholowaychuk","email":"tj@vision-media.ca"}],"directories":{}},"0.0.5":{"name":"component-builder","version":"0.0.5","description":"Component build tool","keywords":["component","build"],"author":{"name":"TJ Holowaychuk","email":"tj@vision-media.caa"},"dependencies":{"batch":"0.1.1","component-require":"0.0.2","debug":"*"},"devDependencies":{"mocha":"*","should":"*"},"main":"index","_id":"component-builder@0.0.5","dist":{"shasum":"bb068b51fd18a5685a3b0487d77ba9710d212d93","tarball":"http://registry.npmjs.org/component-builder/-/component-builder-0.0.5.tgz"},"_npmVersion":"1.1.61","_npmUser":{"name":"tjholowaychuk","email":"tj@vision-media.ca"},"maintainers":[{"name":"tjholowaychuk","email":"tj@vision-media.ca"}],"directories":{}},"0.0.6":{"name":"component-builder","version":"0.0.6","description":"Component build tool","keywords":["component","build"],"author":{"name":"TJ Holowaychuk","email":"tj@vision-media.caa"},"dependencies":{"batch":"0.1.1","component-require":"0.0.2","debug":"*"},"devDependencies":{"mocha":"*","should":"*"},"main":"index","_id":"component-builder@0.0.6","dist":{"shasum":"1aa11af7670bb2adeb93e3d592a0513765d6221a","tarball":"http://registry.npmjs.org/component-builder/-/component-builder-0.0.6.tgz"},"_npmVersion":"1.1.61","_npmUser":{"name":"tjholowaychuk","email":"tj@vision-media.ca"},"maintainers":[{"name":"tjholowaychuk","email":"tj@vision-media.ca"}],"directories":{}},"0.0.7":{"name":"component-builder","version":"0.0.7","description":"Component build tool","keywords":["component","build"],"author":{"name":"TJ Holowaychuk","email":"tj@vision-media.caa"},"dependencies":{"batch":"0.1.1","component-require":"0.0.3","debug":"*"},"devDependencies":{"mocha":"*","should":"*"},"main":"index","_id":"component-builder@0.0.7","dist":{"shasum":"f1ed7017a41c90d64a1cd53483c7901d0dd775dc","tarball":"http://registry.npmjs.org/component-builder/-/component-builder-0.0.7.tgz"},"_npmVersion":"1.1.61","_npmUser":{"name":"tjholowaychuk","email":"tj@vision-media.ca"},"maintainers":[{"name":"tjholowaychuk","email":"tj@vision-media.ca"}],"directories":{}},"0.1.0":{"name":"component-builder","version":"0.1.0","description":"Component build tool","keywords":["component","build"],"author":{"name":"TJ Holowaychuk","email":"tj@vision-media.caa"},"dependencies":{"component-require":"0.1.0","batch":"0.1.1","debug":"*"},"devDependencies":{"mocha":"*","should":"*"},"main":"index","_id":"component-builder@0.1.0","dist":{"shasum":"975a996f1f4ee6911034e8cdac198d45b7fc8774","tarball":"http://registry.npmjs.org/component-builder/-/component-builder-0.1.0.tgz"},"_npmVersion":"1.1.63","_npmUser":{"name":"tjholowaychuk","email":"tj@vision-media.ca"},"maintainers":[{"name":"tjholowaychuk","email":"tj@vision-media.ca"}],"directories":{}},"0.2.0":{"name":"component-builder","version":"0.2.0","description":"Component build tool","keywords":["component","build"],"author":{"name":"TJ Holowaychuk","email":"tj@vision-media.caa"},"dependencies":{"component-require":"0.1.0","batch":"0.1.1","debug":"*"},"devDependencies":{"mocha":"*","should":"*"},"main":"index","_id":"component-builder@0.2.0","dist":{"shasum":"8b0d8dba7ca054a2edddeff42ef71ac2184de299","tarball":"http://registry.npmjs.org/component-builder/-/component-builder-0.2.0.tgz"},"_npmVersion":"1.1.63","_npmUser":{"name":"tjholowaychuk","email":"tj@vision-media.ca"},"maintainers":[{"name":"tjholowaychuk","email":"tj@vision-media.ca"}],"directories":{}},"0.2.1":{"name":"component-builder","version":"0.2.1","description":"Component build tool","keywords":["component","build"],"author":{"name":"TJ Holowaychuk","email":"tj@vision-media.caa"},"dependencies":{"component-require":"0.1.0","batch":"0.1.1","debug":"*"},"devDependencies":{"mocha":"*","should":"*"},"main":"index","_id":"component-builder@0.2.1","dist":{"shasum":"82aa685e20a4d28957a91c6ee51a22f7f39f28c7","tarball":"http://registry.npmjs.org/component-builder/-/component-builder-0.2.1.tgz"},"_npmVersion":"1.1.64","_npmUser":{"name":"tjholowaychuk","email":"tj@vision-media.ca"},"maintainers":[{"name":"tjholowaychuk","email":"tj@vision-media.ca"}],"directories":{}},"0.3.0":{"name":"component-builder","version":"0.3.0","description":"Component build tool","keywords":["component","build"],"author":{"name":"TJ Holowaychuk","email":"tj@vision-media.caa"},"dependencies":{"component-require":"0.1.0","batch":"0.1.1","debug":"*"},"devDependencies":{"mocha":"*","should":"*"},"main":"index","_id":"component-builder@0.3.0","dist":{"shasum":"d1b467357f5c964e5309ad59dc7a15e1d7765326","tarball":"http://registry.npmjs.org/component-builder/-/component-builder-0.3.0.tgz"},"_npmVersion":"1.1.65","_npmUser":{"name":"tjholowaychuk","email":"tj@vision-media.ca"},"maintainers":[{"name":"tjholowaychuk","email":"tj@vision-media.ca"}],"directories":{}},"0.4.0":{"name":"component-builder","version":"0.4.0","description":"Component build tool","keywords":["component","build"],"author":{"name":"TJ Holowaychuk","email":"tj@vision-media.caa"},"dependencies":{"component-require":"0.1.0","batch":"0.1.1","rework":"0.7.0","mkdirp":"0.3.4","debug":"*","better-assert":"~0.1.0"},"devDependencies":{"mocha":"*","should":"*"},"main":"index","_id":"component-builder@0.4.0","dist":{"shasum":"bc8fd6b13d4fc30f77ba5fd0f5213889cc72c92f","tarball":"http://registry.npmjs.org/component-builder/-/component-builder-0.4.0.tgz"},"_npmVersion":"1.1.65","_npmUser":{"name":"tjholowaychuk","email":"tj@vision-media.ca"},"maintainers":[{"name":"tjholowaychuk","email":"tj@vision-media.ca"}],"directories":{}},"0.4.1":{"name":"component-builder","version":"0.4.1","description":"Component build tool","keywords":["component","build"],"author":{"name":"TJ Holowaychuk","email":"tj@vision-media.caa"},"dependencies":{"component-require":"0.1.0","batch":"0.1.1","rework":"0.7.0","mkdirp":"0.3.4","debug":"*","better-assert":"~0.1.0"},"devDependencies":{"mocha":"*","should":"*"},"main":"index","_id":"component-builder@0.4.1","dist":{"shasum":"f98f9d663f1beef5ea6aa2cbaf1247d8487f035d","tarball":"http://registry.npmjs.org/component-builder/-/component-builder-0.4.1.tgz"},"_npmVersion":"1.1.65","_npmUser":{"name":"tjholowaychuk","email":"tj@vision-media.ca"},"maintainers":[{"name":"tjholowaychuk","email":"tj@vision-media.ca"}],"directories":{}},"0.4.2":{"name":"component-builder","version":"0.4.2","description":"Component build tool","keywords":["component","build"],"author":{"name":"TJ Holowaychuk","email":"tj@vision-media.caa"},"dependencies":{"component-require":"0.1.0","batch":"0.1.1","rework":"0.7.0","mkdirp":"0.3.4","debug":"*","better-assert":"~0.1.0"},"devDependencies":{"mocha":"*","should":"*"},"main":"index","_id":"component-builder@0.4.2","dist":{"shasum":"e8b5e7d212bfc6e25793ca40693ffdb41152e40b","tarball":"http://registry.npmjs.org/component-builder/-/component-builder-0.4.2.tgz"},"_npmVersion":"1.1.65","_npmUser":{"name":"tjholowaychuk","email":"tj@vision-media.ca"},"maintainers":[{"name":"tjholowaychuk","email":"tj@vision-media.ca"}],"directories":{}},"0.5.0":{"name":"component-builder","version":"0.5.0","description":"Component build tool","keywords":["component","build"],"author":{"name":"TJ Holowaychuk","email":"tj@vision-media.caa"},"dependencies":{"component-require":"0.1.0","batch":"0.2.1","rework":"0.7.0","mkdirp":"0.3.4","debug":"*","better-assert":"~0.1.0"},"devDependencies":{"mocha":"*","should":"*"},"main":"index","_id":"component-builder@0.5.0","dist":{"shasum":"c72360628a63410d0e6ef2190aae2062958b0706","tarball":"http://registry.npmjs.org/component-builder/-/component-builder-0.5.0.tgz"},"_npmVersion":"1.1.68","_npmUser":{"name":"tjholowaychuk","email":"tj@vision-media.ca"},"maintainers":[{"name":"tjholowaychuk","email":"tj@vision-media.ca"}],"directories":{}},"0.5.1":{"name":"component-builder","version":"0.5.1","description":"Component build tool","keywords":["component","build"],"author":{"name":"TJ Holowaychuk","email":"tj@vision-media.caa"},"dependencies":{"component-require":"0.1.0","batch":"0.2.1","rework":"0.7.0","mkdirp":"0.3.4","debug":"*","better-assert":"~0.1.0"},"devDependencies":{"mocha":"*","should":"*"},"main":"index","_id":"component-builder@0.5.1","dist":{"shasum":"e572d52b0b1eabd7abdede10ccac5210d098e2fd","tarball":"http://registry.npmjs.org/component-builder/-/component-builder-0.5.1.tgz"},"_npmVersion":"1.1.68","_npmUser":{"name":"tjholowaychuk","email":"tj@vision-media.ca"},"maintainers":[{"name":"tjholowaychuk","email":"tj@vision-media.ca"}],"directories":{}},"0.5.2":{"name":"component-builder","version":"0.5.2","description":"Component build tool","keywords":["component","build"],"author":{"name":"TJ Holowaychuk","email":"tj@vision-media.caa"},"dependencies":{"component-require":"0.1.0","batch":"0.2.1","rework":"0.9.1","mkdirp":"0.3.4","debug":"*","better-assert":"~0.1.0"},"devDependencies":{"mocha":"*","should":"*","ejs":"~0.8.3"},"main":"index","_id":"component-builder@0.5.2","dist":{"shasum":"e6353ab9446c7caa27336dba64eef38ab11dc791","tarball":"http://registry.npmjs.org/component-builder/-/component-builder-0.5.2.tgz"},"_npmVersion":"1.1.66","_npmUser":{"name":"tjholowaychuk","email":"tj@vision-media.ca"},"maintainers":[{"name":"tjholowaychuk","email":"tj@vision-media.ca"}],"directories":{}},"0.5.3":{"name":"component-builder","version":"0.5.3","description":"Component build tool","keywords":["component","build"],"author":{"name":"TJ Holowaychuk","email":"tj@vision-media.caa"},"dependencies":{"component-require":"0.1.0","batch":"0.2.1","rework":"0.10.2","mkdirp":"0.3.4","debug":"*","better-assert":"~0.1.0"},"devDependencies":{"mocha":"*","should":"*","ejs":"~0.8.3"},"main":"index","_id":"component-builder@0.5.3","dist":{"shasum":"18991dbfcf7b4094840feaed56ad5aa4648f316b","tarball":"http://registry.npmjs.org/component-builder/-/component-builder-0.5.3.tgz"},"_npmVersion":"1.1.66","_npmUser":{"name":"tjholowaychuk","email":"tj@vision-media.ca"},"maintainers":[{"name":"tjholowaychuk","email":"tj@vision-media.ca"}],"directories":{}},"0.5.5":{"name":"component-builder","version":"0.5.5","description":"Component build tool","keywords":["component","build"],"author":{"name":"TJ Holowaychuk","email":"tj@vision-media.caa"},"dependencies":{"component-require":"0.1.1","batch":"0.2.1","mkdirp":"0.3.4","debug":"*","better-assert":"~0.1.0"},"devDependencies":{"mocha":"*","should":"*","ejs":"~0.8.3"},"main":"index","_id":"component-builder@0.5.5","dist":{"shasum":"6bb7abd0edf7e834e6a7435932a674b3a876b6bb","tarball":"http://registry.npmjs.org/component-builder/-/component-builder-0.5.5.tgz"},"_npmVersion":"1.1.66","_npmUser":{"name":"tjholowaychuk","email":"tj@vision-media.ca"},"maintainers":[{"name":"tjholowaychuk","email":"tj@vision-media.ca"}],"directories":{}},"0.6.0":{"name":"component-builder","version":"0.6.0","description":"Component build tool","keywords":["component","build"],"author":{"name":"TJ Holowaychuk","email":"tj@vision-media.caa"},"dependencies":{"component-require":"0.2.0","batch":"0.2.1","mkdirp":"0.3.4","debug":"*","better-assert":"~0.1.0"},"devDependencies":{"mocha":"*","should":"*","ejs":"~0.8.3"},"main":"index","_id":"component-builder@0.6.0","dist":{"shasum":"a2d00294912513680f5700910e8b487115fd1160","tarball":"http://registry.npmjs.org/component-builder/-/component-builder-0.6.0.tgz"},"_npmVersion":"1.1.66","_npmUser":{"name":"tjholowaychuk","email":"tj@vision-media.ca"},"maintainers":[{"name":"tjholowaychuk","email":"tj@vision-media.ca"}],"directories":{}},"0.6.1":{"name":"component-builder","version":"0.6.1","description":"Component build tool","keywords":["component","build"],"author":{"name":"TJ Holowaychuk","email":"tj@vision-media.caa"},"dependencies":{"component-require":"0.2.0","batch":"0.2.1","mkdirp":"0.3.4","debug":"*","better-assert":"~0.1.0"},"devDependencies":{"mocha":"*","should":"*","ejs":"~0.8.3"},"main":"index","_id":"component-builder@0.6.1","dist":{"shasum":"aefe486a51d6acacdc6b5e538dc03483d7652ffb","tarball":"http://registry.npmjs.org/component-builder/-/component-builder-0.6.1.tgz"},"_npmVersion":"1.1.66","_npmUser":{"name":"tjholowaychuk","email":"tj@vision-media.ca"},"maintainers":[{"name":"tjholowaychuk","email":"tj@vision-media.ca"}],"directories":{}},"0.6.2":{"name":"component-builder","version":"0.6.2","description":"Component build tool","keywords":["component","build"],"author":{"name":"TJ Holowaychuk","email":"tj@vision-media.caa"},"dependencies":{"component-require":"0.2.0","batch":"0.2.1","mkdirp":"0.3.4","debug":"*","better-assert":"~0.1.0"},"devDependencies":{"mocha":"*","should":"*","ejs":"~0.8.3"},"main":"index","_id":"component-builder@0.6.2","dist":{"shasum":"ffaf3ced80be3ecaf53377e05d6650e54df6bfaa","tarball":"http://registry.npmjs.org/component-builder/-/component-builder-0.6.2.tgz"},"_npmVersion":"1.1.66","_npmUser":{"name":"tjholowaychuk","email":"tj@vision-media.ca"},"maintainers":[{"name":"tjholowaychuk","email":"tj@vision-media.ca"}],"directories":{}},"0.6.3":{"name":"component-builder","version":"0.6.3","description":"Component build tool","keywords":["component","build"],"author":{"name":"TJ Holowaychuk","email":"tj@vision-media.caa"},"dependencies":{"component-require":"0.2.0","batch":"0.2.1","mkdirp":"0.3.4","debug":"*","better-assert":"~0.1.0","fs-extra":"~0.5.0"},"devDependencies":{"mocha":"*","should":"*","ejs":"~0.8.3"},"main":"index","_id":"component-builder@0.6.3","dist":{"shasum":"d42abce0a8c741598d922121a05f5725c48ce7ed","tarball":"http://registry.npmjs.org/component-builder/-/component-builder-0.6.3.tgz"},"_from":".","_npmVersion":"1.2.2","_npmUser":{"name":"tjholowaychuk","email":"tj@vision-media.ca"},"maintainers":[{"name":"tjholowaychuk","email":"tj@vision-media.ca"}],"directories":{}},"0.6.4":{"name":"component-builder","version":"0.6.4","description":"Component build tool","keywords":["component","build"],"author":{"name":"TJ Holowaychuk","email":"tj@vision-media.caa"},"dependencies":{"component-require":"0.2.1","batch":"0.2.1","mkdirp":"0.3.4","debug":"*","better-assert":"~0.1.0","fs-extra":"~0.5.0"},"devDependencies":{"mocha":"*","should":"*","ejs":"~0.8.3"},"main":"index","_id":"component-builder@0.6.4","dist":{"shasum":"ca94b26dc8b23e5169db1d44b1ee834a3dd04764","tarball":"http://registry.npmjs.org/component-builder/-/component-builder-0.6.4.tgz"},"_from":".","_npmVersion":"1.2.14","_npmUser":{"name":"tjholowaychuk","email":"tj@vision-media.ca"},"maintainers":[{"name":"tjholowaychuk","email":"tj@vision-media.ca"}],"directories":{}},"0.6.5":{"name":"component-builder","version":"0.6.5","description":"Component build tool","keywords":["component","build"],"author":{"name":"TJ Holowaychuk","email":"tj@vision-media.caa"},"dependencies":{"component-require":"0.2.1","batch":"0.2.1","mkdirp":"0.3.4","debug":"*","better-assert":"~0.1.0","fs-extra":"~0.5.0"},"devDependencies":{"mocha":"*","should":"*","ejs":"~0.8.3"},"main":"index","_id":"component-builder@0.6.5","dist":{"shasum":"33f6d5a62f250e5c242e8a592f56ec3f5f4ece98","tarball":"http://registry.npmjs.org/component-builder/-/component-builder-0.6.5.tgz"},"_from":".","_npmVersion":"1.2.14","_npmUser":{"name":"tjholowaychuk","email":"tj@vision-media.ca"},"maintainers":[{"name":"tjholowaychuk","email":"tj@vision-media.ca"}],"directories":{}},"0.7.0":{"name":"component-builder","version":"0.7.0","description":"Component build tool","keywords":["component","build"],"author":{"name":"TJ Holowaychuk","email":"tj@vision-media.caa"},"dependencies":{"component-require":"0.2.1","batch":"0.2.1","mkdirp":"0.3.4","debug":"*","better-assert":"~0.1.0","fs-extra":"~0.6.0"},"devDependencies":{"mocha":"*","should":"*","ejs":"~0.8.3"},"main":"index","_id":"component-builder@0.7.0","dist":{"shasum":"64997c3e57f596f7523b359f8c1707512bbff390","tarball":"http://registry.npmjs.org/component-builder/-/component-builder-0.7.0.tgz"},"_from":".","_npmVersion":"1.2.14","_npmUser":{"name":"tjholowaychuk","email":"tj@vision-media.ca"},"maintainers":[{"name":"tjholowaychuk","email":"tj@vision-media.ca"}],"directories":{}},"0.7.1":{"name":"component-builder","version":"0.7.1","description":"Component build tool","keywords":["component","build"],"author":{"name":"TJ Holowaychuk","email":"tj@vision-media.caa"},"dependencies":{"component-require":"0.2.1","batch":"0.2.1","mkdirp":"0.3.4","debug":"*","better-assert":"~0.1.0","fs-extra":"~0.6.0"},"devDependencies":{"mocha":"*","should":"*","ejs":"~0.8.3"},"main":"index","_id":"component-builder@0.7.1","dist":{"shasum":"6b74d1b2b2b1268d7b0c51511c9189625ff5c324","tarball":"http://registry.npmjs.org/component-builder/-/component-builder-0.7.1.tgz"},"_from":".","_npmVersion":"1.2.14","_npmUser":{"name":"tjholowaychuk","email":"tj@vision-media.ca"},"maintainers":[{"name":"tjholowaychuk","email":"tj@vision-media.ca"}],"directories":{}},"0.8.0":{"name":"component-builder","version":"0.8.0","description":"Component build tool","keywords":["component","build"],"author":{"name":"TJ Holowaychuk","email":"tj@vision-media.caa"},"dependencies":{"component-require":"0.2.1","batch":"0.2.1","mkdirp":"0.3.4","debug":"*","better-assert":"~0.1.0","fs-extra":"~0.6.0"},"devDependencies":{"mocha":"*","should":"*","ejs":"~0.8.3"},"main":"index","_id":"component-builder@0.8.0","dist":{"shasum":"40f163837c085a332aa3825beb00eae1e21e75b5","tarball":"http://registry.npmjs.org/component-builder/-/component-builder-0.8.0.tgz"},"_from":".","_npmVersion":"1.2.14","_npmUser":{"name":"tjholowaychuk","email":"tj@vision-media.ca"},"maintainers":[{"name":"tjholowaychuk","email":"tj@vision-media.ca"}],"directories":{}},"0.8.1":{"name":"component-builder","version":"0.8.1","description":"Component build tool","keywords":["component","build"],"author":{"name":"TJ Holowaychuk","email":"tj@vision-media.caa"},"dependencies":{"component-require":"0.2.1","batch":"0.2.1","mkdirp":"0.3.4","debug":"*","better-assert":"~0.1.0","fs-extra":"~0.6.0"},"devDependencies":{"mocha":"*","should":"*","ejs":"~0.8.3"},"repository":{"type":"git","url":"https://github.com/component/builder.js.git"},"main":"index","_id":"component-builder@0.8.1","dist":{"shasum":"553bf5ce8e28f3e62ab8b4fa0903c4fc6c66d407","tarball":"http://registry.npmjs.org/component-builder/-/component-builder-0.8.1.tgz"},"_from":".","_npmVersion":"1.2.14","_npmUser":{"name":"tjholowaychuk","email":"tj@vision-media.ca"},"maintainers":[{"name":"tjholowaychuk","email":"tj@vision-media.ca"}],"directories":{}},"0.8.2":{"name":"component-builder","version":"0.8.2","description":"Component build tool","keywords":["component","build"],"author":{"name":"TJ Holowaychuk","email":"tj@vision-media.caa"},"dependencies":{"component-require":"0.2.1","batch":"0.2.1","mkdirp":"0.3.4","debug":"*","better-assert":"~0.1.0","fs-extra":"~0.6.0"},"devDependencies":{"mocha":"*","should":"*","ejs":"~0.8.3"},"repository":{"type":"git","url":"https://github.com/component/builder.js.git"},"main":"index","_id":"component-builder@0.8.2","dist":{"shasum":"3dfcab2566f7ea67011c3727afaa64bd322653ce","tarball":"http://registry.npmjs.org/component-builder/-/component-builder-0.8.2.tgz"},"_from":".","_npmVersion":"1.2.14","_npmUser":{"name":"tjholowaychuk","email":"tj@vision-media.ca"},"maintainers":[{"name":"tjholowaychuk","email":"tj@vision-media.ca"}],"directories":{}},"0.8.3":{"name":"component-builder","version":"0.8.3","description":"Component build tool","keywords":["component","build"],"author":{"name":"TJ Holowaychuk","email":"tj@vision-media.caa"},"dependencies":{"component-require":"0.2.2","batch":"0.2.1","mkdirp":"0.3.4","debug":"*","better-assert":"~0.1.0","fs-extra":"~0.6.0"},"devDependencies":{"mocha":"*","should":"*","ejs":"~0.8.3"},"repository":{"type":"git","url":"https://github.com/component/builder.js.git"},"main":"index","_id":"component-builder@0.8.3","dist":{"shasum":"c455f5d4265b6ad73b28f001de0e9893e0259cd4","tarball":"http://registry.npmjs.org/component-builder/-/component-builder-0.8.3.tgz"},"_from":".","_npmVersion":"1.2.14","_npmUser":{"name":"tjholowaychuk","email":"tj@vision-media.ca"},"maintainers":[{"name":"tjholowaychuk","email":"tj@vision-media.ca"}],"directories":{}},"0.9.0":{"name":"component-builder","version":"0.9.0","description":"Component build tool","keywords":["component","build"],"author":{"name":"TJ Holowaychuk","email":"tj@vision-media.caa"},"dependencies":{"component-require":"0.2.2","batch":"0.2.1","mkdirp":"0.3.4","debug":"*","better-assert":"~0.1.0","cp":"~0.1.0","string-to-js":"0.0.1"},"devDependencies":{"mocha":"*","should":"*","ejs":"~0.8.3","styl":"0.2.2"},"repository":{"type":"git","url":"https://github.com/component/builder.js.git"},"main":"index","bugs":{"url":"https://github.com/component/builder.js/issues"},"_id":"component-builder@0.9.0","dist":{"shasum":"f345772b5b4b8b8ce083483df01d783be137d1b8","tarball":"http://registry.npmjs.org/component-builder/-/component-builder-0.9.0.tgz"},"_from":".","_npmVersion":"1.2.30","_npmUser":{"name":"tjholowaychuk","email":"tj@vision-media.ca"},"maintainers":[{"name":"tjholowaychuk","email":"tj@vision-media.ca"}],"directories":{}},"0.9.1":{"name":"component-builder","version":"0.9.1","description":"Component build tool","keywords":["component","build"],"author":{"name":"TJ Holowaychuk","email":"tj@vision-media.caa"},"dependencies":{"component-require":"0.3.0","batch":"0.2.1","mkdirp":"0.3.4","debug":"*","better-assert":"~0.1.0","cp":"~0.1.0","string-to-js":"0.0.1"},"devDependencies":{"mocha":"*","should":"*","ejs":"~0.8.3","styl":"0.2.2"},"repository":{"type":"git","url":"https://github.com/component/builder.js.git"},"main":"index","bugs":{"url":"https://github.com/component/builder.js/issues"},"_id":"component-builder@0.9.1","dist":{"shasum":"518eb974e4c26ebe37df7f2539340752620ac8c8","tarball":"http://registry.npmjs.org/component-builder/-/component-builder-0.9.1.tgz"},"_from":".","_npmVersion":"1.3.8","_npmUser":{"name":"tjholowaychuk","email":"tj@vision-media.ca"},"maintainers":[{"name":"tjholowaychuk","email":"tj@vision-media.ca"}],"directories":{}},"0.9.2":{"name":"component-builder","version":"0.9.2","description":"Component build tool","keywords":["component","build"],"author":{"name":"TJ Holowaychuk","email":"tj@vision-media.caa"},"dependencies":{"component-require":"0.3.1","batch":"0.2.1","mkdirp":"0.3.4","debug":"*","better-assert":"~0.1.0","cp":"~0.1.0","string-to-js":"0.0.1"},"devDependencies":{"mocha":"*","should":"*","ejs":"~0.8.3","styl":"0.2.2"},"repository":{"type":"git","url":"https://github.com/component/builder.js.git"},"main":"index","bugs":{"url":"https://github.com/component/builder.js/issues"},"_id":"component-builder@0.9.2","dist":{"shasum":"78b59e82ef174420a2067e702780fa0d17ab6947","tarball":"http://registry.npmjs.org/component-builder/-/component-builder-0.9.2.tgz"},"_from":".","_npmVersion":"1.2.30","_npmUser":{"name":"tjholowaychuk","email":"tj@vision-media.ca"},"maintainers":[{"name":"tjholowaychuk","email":"tj@vision-media.ca"}],"directories":{}},"0.10.0":{"name":"component-builder","version":"0.10.0","description":"Component build tool","keywords":["component","build"],"author":{"name":"TJ Holowaychuk","email":"tj@vision-media.caa"},"dependencies":{"component-require":"0.3.1","batch":"0.2.1","mkdirp":"0.3.4","debug":"*","better-assert":"~0.1.0","cp":"~0.1.0","string-to-js":"0.0.1"},"devDependencies":{"mocha":"*","should":"*","ejs":"~0.8.3","styl":"0.2.2"},"repository":{"type":"git","url":"https://github.com/component/builder.js.git"},"main":"index","bugs":{"url":"https://github.com/component/builder.js/issues"},"_id":"component-builder@0.10.0","dist":{"shasum":"5e9eefad6e283b4eba839a536c625bcf6ff9245f","tarball":"http://registry.npmjs.org/component-builder/-/component-builder-0.10.0.tgz"},"_from":".","_npmVersion":"1.2.30","_npmUser":{"name":"tjholowaychuk","email":"tj@vision-media.ca"},"maintainers":[{"name":"tjholowaychuk","email":"tj@vision-media.ca"}],"directories":{}},"0.11.0":{"name":"component-builder","version":"0.11.0","description":"Component build tool","keywords":["component","build"],"author":{"name":"TJ Holowaychuk","email":"tj@vision-media.caa"},"dependencies":{"component-require":"1.0.0","batch":"0.2.1","mkdirp":"0.3.4","debug":"*","cp":"~0.1.0","string-to-js":"0.0.1","requires":"~1.0.0"},"devDependencies":{"mocha":"*","should":"1.x","ejs":"~0.8.3","styl":"0.2.2","better-assert":"~0.1.0"},"repository":{"type":"git","url":"https://github.com/component/builder.js.git"},"main":"index","bugs":{"url":"https://github.com/component/builder.js/issues"},"homepage":"https://github.com/component/builder.js","_id":"component-builder@0.11.0","dist":{"shasum":"fd725e80c1cbca02e9a6b59c5d9e9d02f9f53ff8","tarball":"http://registry.npmjs.org/component-builder/-/component-builder-0.11.0.tgz"},"_from":".","_npmVersion":"1.3.15","_npmUser":{"name":"tjholowaychuk","email":"tj@vision-media.ca"},"maintainers":[{"name":"tjholowaychuk","email":"tj@vision-media.ca"},{"name":"jongleberry","email":"jonathanrichardong@gmail.com"}],"directories":{}},"0.11.1":{"name":"component-builder","version":"0.11.1","description":"Component build tool","keywords":["component","build"],"author":{"name":"TJ Holowaychuk","email":"tj@vision-media.caa"},"dependencies":{"component-require":"1.0.0","batch":"0.2.1","mkdirp":"0.3.4","debug":"*","cp":"~0.1.0","string-to-js":"0.0.1","requires":"~1.0.0"},"devDependencies":{"mocha":"*","should":"1.x","ejs":"~0.8.3","styl":"0.2.2","better-assert":"~0.1.0"},"repository":{"type":"git","url":"https://github.com/component/builder.js.git"},"main":"index","bugs":{"url":"https://github.com/component/builder.js/issues"},"homepage":"https://github.com/component/builder.js","_id":"component-builder@0.11.1","dist":{"shasum":"5a2919b9dc766e8591985c8a0eeb3c64e81ef5d4","tarball":"http://registry.npmjs.org/component-builder/-/component-builder-0.11.1.tgz"},"_from":".","_npmVersion":"1.3.15","_npmUser":{"name":"tjholowaychuk","email":"tj@vision-media.ca"},"maintainers":[{"name":"tjholowaychuk","email":"tj@vision-media.ca"},{"name":"jongleberry","email":"jonathanrichardong@gmail.com"}],"directories":{}},"0.11.2":{"name":"component-builder","version":"0.11.2","description":"Component build tool","keywords":["component","build"],"author":{"name":"TJ Holowaychuk","email":"tj@vision-media.caa"},"dependencies":{"component-require":"1.0.1","batch":"0.2.1","mkdirp":"0.3.4","debug":"*","cp":"~0.1.0","string-to-js":"0.0.1","requires":"~1.0.0"},"devDependencies":{"mocha":"*","should":"1.x","ejs":"~0.8.3","styl":"0.2.2","better-assert":"~0.1.0"},"repository":{"type":"git","url":"https://github.com/component/builder.js.git"},"main":"index","bugs":{"url":"https://github.com/component/builder.js/issues"},"homepage":"https://github.com/component/builder.js","_id":"component-builder@0.11.2","dist":{"shasum":"2c70265d90924f39fc92a0340018b9a4597ece90","tarball":"http://registry.npmjs.org/component-builder/-/component-builder-0.11.2.tgz"},"_from":".","_npmVersion":"1.3.15","_npmUser":{"name":"tjholowaychuk","email":"tj@vision-media.ca"},"maintainers":[{"name":"tjholowaychuk","email":"tj@vision-media.ca"},{"name":"jongleberry","email":"jonathanrichardong@gmail.com"}],"directories":{}},"0.10.1":{"name":"component-builder","version":"0.10.1","description":"Component build tool","keywords":["component","build"],"author":{"name":"TJ Holowaychuk","email":"tj@vision-media.caa"},"dependencies":{"component-require":"0.3.1","batch":"0.2.1","mkdirp":"0.3.4","debug":"*","cp":"~0.1.0","string-to-js":"0.0.1"},"devDependencies":{"mocha":"*","should":"*","ejs":"~0.8.3","styl":"0.2.2","better-assert":"~0.1.0"},"repository":{"type":"git","url":"https://github.com/component/builder.js.git"},"main":"index","bugs":{"url":"https://github.com/component/builder.js/issues"},"homepage":"https://github.com/component/builder.js","_id":"component-builder@0.10.1","dist":{"shasum":"d29c7ab70241a678e3f8dbea4d1759c68b6f8f9b","tarball":"http://registry.npmjs.org/component-builder/-/component-builder-0.10.1.tgz"},"_from":".","_npmVersion":"1.3.15","_npmUser":{"name":"tjholowaychuk","email":"tj@vision-media.ca"},"maintainers":[{"name":"tjholowaychuk","email":"tj@vision-media.ca"},{"name":"jongleberry","email":"jonathanrichardong@gmail.com"}],"directories":{}},"0.12.0":{"name":"component-builder","version":"0.12.0","description":"Component build tool","keywords":["component","build"],"author":{"name":"TJ Holowaychuk","email":"tj@vision-media.caa"},"dependencies":{"component-require":"0.3.1","batch":"0.5.0","mkdirp":"0.3.4","debug":"*","cp":"~0.1.0","string-to-js":"0.0.1","requires":"~1.0.0"},"devDependencies":{"mocha":"*","should":"1.x","ejs":"~0.8.3","styl":"0.2.2","better-assert":"~0.1.0"},"repository":{"type":"git","url":"https://github.com/component/builder.js.git"},"main":"index","bugs":{"url":"https://github.com/component/builder.js/issues"},"homepage":"https://github.com/component/builder.js","_id":"component-builder@0.12.0","dist":{"shasum":"a9d46f2372d9468752f075ae878fc7ba8f1ef34e","tarball":"http://registry.npmjs.org/component-builder/-/component-builder-0.12.0.tgz"},"_from":".","_npmVersion":"1.3.23","_npmUser":{"name":"tjholowaychuk","email":"tj@vision-media.ca"},"maintainers":[{"name":"tjholowaychuk","email":"tj@vision-media.ca"}],"directories":{}},"1.0.0":{"name":"component-builder","description":"builder for component","version":"1.0.0","author":{"name":"Jonathan Ong","email":"me@jongleberry.com","url":"http://jongleberry.com"},"license":"MIT","repository":{"type":"git","url":"component/builder2.js"},"dependencies":{"debug":"*","generator-supported":"~0.0.1","component-flatten":"^1.0.0","component-manifest":"^1.0.0","component-require2":"~0.1.0","css-url-rewriter":"~0.0.1","syntax-error":"^1.1.0","requires":"^1.0.0","graceful-fs":"^2.0.1","mkdirp":"~0.3.5","cp":"~0.1.1","chanel":"^2.0.0","co":"^3.0.2"},"devDependencies":{"component-resolver":"^1.0.0","builder-es6-module-to-cjs":"^1.0.0","rimraf":"^2.2.6","mocha":"^1.17.0","should":"^3.0.0","gnode":"0","regenerator":"0"},"scripts":{"test":"NODE=gnode make test","prepublish":"make clean build"},"_id":"component-builder@1.0.0","dist":{"shasum":"3cba925f1e9249c4368053365d4eec89041c0220","tarball":"http://registry.npmjs.org/component-builder/-/component-builder-1.0.0.tgz"},"_from":".","_npmVersion":"1.4.6","_npmUser":{"name":"jongleberry","email":"jonathanrichardong@gmail.com"},"maintainers":[{"name":"tjholowaychuk","email":"tj@vision-media.ca"},{"name":"jongleberry","email":"jonathanrichardong@gmail.com"},{"name":"dominicbarnes","email":"dominic@dbarnes.info"},{"name":"tootallnate","email":"nathan@tootallnate.net"},{"name":"rauchg","email":"rauchg@gmail.com"},{"name":"retrofox","email":"rdsuarez@gmail.com"},{"name":"coreh","email":"thecoreh@gmail.com"},{"name":"forbeslindesay","email":"forbes@lindesay.co.uk"},{"name":"kelonye","email":"kelonyemitchel@gmail.com"},{"name":"mattmueller","email":"mattmuelle@gmail.com"},{"name":"yields","email":"yields@icloud.com"},{"name":"anthonyshort","email":"antshort@gmail.com"},{"name":"ianstormtaylor","email":"ian@ianstormtaylor.com"},{"name":"cristiandouce","email":"cristian@gravityonmars.com"},{"name":"swatinem","email":"arpad.borsos@googlemail.com"},{"name":"stagas","email":"gstagas@gmail.com"},{"name":"amasad","email":"amjad.masad@gmail.com"},{"name":"juliangruber","email":"julian@juliangruber.com"},{"name":"shtylman","email":"shtylman@gmail.com"},{"name":"calvinfo","email":"calvin@calv.info"},{"name":"blakeembrey","email":"hello@blakeembrey.com"}],"directories":{}},"1.0.1":{"name":"component-builder","description":"builder for component","version":"1.0.1","author":{"name":"Jonathan Ong","email":"me@jongleberry.com","url":"http://jongleberry.com"},"license":"MIT","repository":{"type":"git","url":"component/builder2.js"},"dependencies":{"debug":"*","generator-supported":"~0.0.1","component-flatten":"^1.0.0","component-manifest":"^1.0.0","component-require2":"^1.0.0","css-url-rewriter":"~0.0.1","syntax-error":"^1.1.0","requires":"^1.0.0","graceful-fs":"^2.0.1","mkdirp":"~0.3.5","cp":"~0.1.1","chanel":"^2.0.0","co":"^3.0.2"},"devDependencies":{"component-resolver":"^1.0.0","builder-es6-module-to-cjs":"^1.0.0","rimraf":"^2.2.6","mocha":"^1.17.0","should":"^3.0.0","gnode":"0","regenerator":"0"},"scripts":{"test":"NODE=gnode make test","prepublish":"make clean build"},"_id":"component-builder@1.0.1","dist":{"shasum":"9f84253ad33d4edc9a76b59962f042b669596a84","tarball":"http://registry.npmjs.org/component-builder/-/component-builder-1.0.1.tgz"},"_from":".","_npmVersion":"1.4.3","_npmUser":{"name":"jongleberry","email":"jonathanrichardong@gmail.com"},"maintainers":[{"name":"tjholowaychuk","email":"tj@vision-media.ca"},{"name":"jongleberry","email":"jonathanrichardong@gmail.com"},{"name":"dominicbarnes","email":"dominic@dbarnes.info"},{"name":"tootallnate","email":"nathan@tootallnate.net"},{"name":"rauchg","email":"rauchg@gmail.com"},{"name":"retrofox","email":"rdsuarez@gmail.com"},{"name":"coreh","email":"thecoreh@gmail.com"},{"name":"forbeslindesay","email":"forbes@lindesay.co.uk"},{"name":"kelonye","email":"kelonyemitchel@gmail.com"},{"name":"mattmueller","email":"mattmuelle@gmail.com"},{"name":"yields","email":"yields@icloud.com"},{"name":"anthonyshort","email":"antshort@gmail.com"},{"name":"ianstormtaylor","email":"ian@ianstormtaylor.com"},{"name":"cristiandouce","email":"cristian@gravityonmars.com"},{"name":"swatinem","email":"arpad.borsos@googlemail.com"},{"name":"stagas","email":"gstagas@gmail.com"},{"name":"amasad","email":"amjad.masad@gmail.com"},{"name":"juliangruber","email":"julian@juliangruber.com"},{"name":"shtylman","email":"shtylman@gmail.com"},{"name":"calvinfo","email":"calvin@calv.info"},{"name":"blakeembrey","email":"hello@blakeembrey.com"}],"directories":{}},"1.0.2":{"name":"component-builder","description":"builder for component","version":"1.0.2","author":{"name":"Jonathan Ong","email":"me@jongleberry.com","url":"http://jongleberry.com"},"license":"MIT","repository":{"type":"git","url":"component/builder2.js"},"dependencies":{"debug":"*","generator-supported":"~0.0.1","component-flatten":"^1.0.0","component-manifest":"^1.0.0","component-require2":"^1.0.0","css-url-rewriter":"~0.0.1","syntax-error":"^1.1.0","requires":"^1.0.0","graceful-fs":"^2.0.1","mkdirp":"~0.3.5","cp":"~0.1.1","chanel":"^2.0.0","co":"^3.0.2"},"devDependencies":{"component-resolver":"^1.0.0","builder-es6-module-to-cjs":"^1.0.0","rimraf":"^2.2.6","mocha":"^1.17.0","should":"^3.0.0","gnode":"0","regenerator":"0"},"scripts":{"test":"NODE=gnode make test","prepublish":"make clean build"},"_id":"component-builder@1.0.2","dist":{"shasum":"ac64591e0f5419b63761bbb06fa7d24cc1186d72","tarball":"http://registry.npmjs.org/component-builder/-/component-builder-1.0.2.tgz"},"_from":".","_npmVersion":"1.4.6","_npmUser":{"name":"jongleberry","email":"jonathanrichardong@gmail.com"},"maintainers":[{"name":"tjholowaychuk","email":"tj@vision-media.ca"},{"name":"jongleberry","email":"jonathanrichardong@gmail.com"},{"name":"dominicbarnes","email":"dominic@dbarnes.info"},{"name":"tootallnate","email":"nathan@tootallnate.net"},{"name":"rauchg","email":"rauchg@gmail.com"},{"name":"retrofox","email":"rdsuarez@gmail.com"},{"name":"coreh","email":"thecoreh@gmail.com"},{"name":"forbeslindesay","email":"forbes@lindesay.co.uk"},{"name":"kelonye","email":"kelonyemitchel@gmail.com"},{"name":"mattmueller","email":"mattmuelle@gmail.com"},{"name":"yields","email":"yields@icloud.com"},{"name":"anthonyshort","email":"antshort@gmail.com"},{"name":"ianstormtaylor","email":"ian@ianstormtaylor.com"},{"name":"cristiandouce","email":"cristian@gravityonmars.com"},{"name":"swatinem","email":"arpad.borsos@googlemail.com"},{"name":"stagas","email":"gstagas@gmail.com"},{"name":"amasad","email":"amjad.masad@gmail.com"},{"name":"juliangruber","email":"julian@juliangruber.com"},{"name":"shtylman","email":"shtylman@gmail.com"},{"name":"calvinfo","email":"calvin@calv.info"},{"name":"blakeembrey","email":"hello@blakeembrey.com"}],"directories":{}},"1.0.3":{"name":"component-builder","description":"builder for component","version":"1.0.3","author":{"name":"Jonathan Ong","email":"me@jongleberry.com","url":"http://jongleberry.com"},"license":"MIT","repository":{"type":"git","url":"component/builder2.js"},"dependencies":{"debug":"*","generator-supported":"~0.0.1","component-flatten":"^1.0.0","component-manifest":"^1.0.0","component-require2":"^1.0.0","css-url-rewriter":"~0.0.1","syntax-error":"^1.1.0","requires":"^1.0.0","graceful-fs":"^2.0.1","mkdirp":"~0.3.5","cp":"~0.1.1","chanel":"^2.0.0","co":"^3.0.2"},"devDependencies":{"component-resolver":"^1.0.0","builder-es6-module-to-cjs":"^1.0.0","rimraf":"^2.2.6","mocha":"^1.17.0","should":"^3.0.0","gnode":"0","regenerator":"0"},"scripts":{"test":"NODE=gnode make test","prepublish":"make clean build"},"_id":"component-builder@1.0.3","dist":{"shasum":"c5f49ea2585a7e262726b3215f2ee17821f4fd8d","tarball":"http://registry.npmjs.org/component-builder/-/component-builder-1.0.3.tgz"},"_from":".","_npmVersion":"1.4.6","_npmUser":{"name":"jongleberry","email":"jonathanrichardong@gmail.com"},"maintainers":[{"name":"tjholowaychuk","email":"tj@vision-media.ca"},{"name":"jongleberry","email":"jonathanrichardong@gmail.com"},{"name":"dominicbarnes","email":"dominic@dbarnes.info"},{"name":"tootallnate","email":"nathan@tootallnate.net"},{"name":"rauchg","email":"rauchg@gmail.com"},{"name":"retrofox","email":"rdsuarez@gmail.com"},{"name":"coreh","email":"thecoreh@gmail.com"},{"name":"forbeslindesay","email":"forbes@lindesay.co.uk"},{"name":"kelonye","email":"kelonyemitchel@gmail.com"},{"name":"mattmueller","email":"mattmuelle@gmail.com"},{"name":"yields","email":"yields@icloud.com"},{"name":"anthonyshort","email":"antshort@gmail.com"},{"name":"ianstormtaylor","email":"ian@ianstormtaylor.com"},{"name":"cristiandouce","email":"cristian@gravityonmars.com"},{"name":"swatinem","email":"arpad.borsos@googlemail.com"},{"name":"stagas","email":"gstagas@gmail.com"},{"name":"amasad","email":"amjad.masad@gmail.com"},{"name":"juliangruber","email":"julian@juliangruber.com"},{"name":"shtylman","email":"shtylman@gmail.com"},{"name":"calvinfo","email":"calvin@calv.info"},{"name":"blakeembrey","email":"hello@blakeembrey.com"}],"directories":{}},"1.0.4":{"name":"component-builder","description":"builder for component","version":"1.0.4","author":{"name":"Jonathan Ong","email":"me@jongleberry.com","url":"http://jongleberry.com"},"license":"MIT","repository":{"type":"git","url":"component/builder2.js"},"dependencies":{"debug":"*","generator-supported":"~0.0.1","component-flatten":"^1.0.0","component-manifest":"^1.0.0","component-require2":"^1.0.0","css-url-rewriter":"~0.0.1","syntax-error":"^1.1.0","requires":"^1.0.0","graceful-fs":"^2.0.1","mkdirp":"~0.3.5","cp":"~0.1.1","chanel":"^2.0.0","co":"^3.0.2"},"devDependencies":{"component-resolver":"^1.0.0","builder-es6-module-to-cjs":"^1.0.0","rimraf":"^2.2.6","mocha":"^1.17.0","should":"^3.0.0","gnode":"0","regenerator":"0"},"scripts":{"test":"NODE=gnode make test","prepublish":"make clean build"},"_id":"component-builder@1.0.4","dist":{"shasum":"7d51f452bd8d27b335ff3edc5648690f3c58eaf0","tarball":"http://registry.npmjs.org/component-builder/-/component-builder-1.0.4.tgz"},"_from":".","_npmVersion":"1.4.6","_npmUser":{"name":"jongleberry","email":"jonathanrichardong@gmail.com"},"maintainers":[{"name":"tjholowaychuk","email":"tj@vision-media.ca"},{"name":"jongleberry","email":"jonathanrichardong@gmail.com"},{"name":"dominicbarnes","email":"dominic@dbarnes.info"},{"name":"tootallnate","email":"nathan@tootallnate.net"},{"name":"rauchg","email":"rauchg@gmail.com"},{"name":"retrofox","email":"rdsuarez@gmail.com"},{"name":"coreh","email":"thecoreh@gmail.com"},{"name":"forbeslindesay","email":"forbes@lindesay.co.uk"},{"name":"kelonye","email":"kelonyemitchel@gmail.com"},{"name":"mattmueller","email":"mattmuelle@gmail.com"},{"name":"yields","email":"yields@icloud.com"},{"name":"anthonyshort","email":"antshort@gmail.com"},{"name":"ianstormtaylor","email":"ian@ianstormtaylor.com"},{"name":"cristiandouce","email":"cristian@gravityonmars.com"},{"name":"swatinem","email":"arpad.borsos@googlemail.com"},{"name":"stagas","email":"gstagas@gmail.com"},{"name":"amasad","email":"amjad.masad@gmail.com"},{"name":"juliangruber","email":"julian@juliangruber.com"},{"name":"shtylman","email":"shtylman@gmail.com"},{"name":"calvinfo","email":"calvin@calv.info"},{"name":"blakeembrey","email":"hello@blakeembrey.com"},{"name":"timoxley","email":"secoif@gmail.com"},{"name":"jonathanong","email":"jonathanrichardong@gmail.com"}],"directories":{}},"1.1.0":{"name":"component-builder","description":"builder for component","version":"1.1.0","author":{"name":"Jonathan Ong","email":"me@jongleberry.com","url":"http://jongleberry.com"},"license":"MIT","repository":{"type":"git","url":"component/builder2.js"},"dependencies":{"debug":"*","generator-supported":"~0.0.1","component-flatten":"^1.0.0","component-manifest":"^1.0.0","component-require2":"^1.0.0","css-url-rewriter":"~0.0.1","syntax-error":"^1.1.0","requires":"^1.0.0","graceful-fs":"^2.0.1","mkdirp":"~0.3.5","cp":"~0.1.1","chanel":"^2.0.0","co":"^3.0.2"},"devDependencies":{"component-resolver":"^1.0.0","builder-es6-module-to-cjs":"^1.0.0","rimraf":"^2.2.6","mocha":"^1.17.0","should":"^3.0.0","gnode":"0","regenerator":"0"},"scripts":{"test":"NODE=gnode make test","prepublish":"make clean build"},"_id":"component-builder@1.1.0","dist":{"shasum":"9cae65176f47f5d42c2a11445d55f0c6062ee390","tarball":"http://registry.npmjs.org/component-builder/-/component-builder-1.1.0.tgz"},"_from":".","_npmVersion":"1.4.6","_npmUser":{"name":"jongleberry","email":"jonathanrichardong@gmail.com"},"maintainers":[{"name":"tjholowaychuk","email":"tj@vision-media.ca"},{"name":"jongleberry","email":"jonathanrichardong@gmail.com"},{"name":"dominicbarnes","email":"dominic@dbarnes.info"},{"name":"tootallnate","email":"nathan@tootallnate.net"},{"name":"rauchg","email":"rauchg@gmail.com"},{"name":"retrofox","email":"rdsuarez@gmail.com"},{"name":"coreh","email":"thecoreh@gmail.com"},{"name":"forbeslindesay","email":"forbes@lindesay.co.uk"},{"name":"kelonye","email":"kelonyemitchel@gmail.com"},{"name":"mattmueller","email":"mattmuelle@gmail.com"},{"name":"yields","email":"yields@icloud.com"},{"name":"anthonyshort","email":"antshort@gmail.com"},{"name":"ianstormtaylor","email":"ian@ianstormtaylor.com"},{"name":"cristiandouce","email":"cristian@gravityonmars.com"},{"name":"swatinem","email":"arpad.borsos@googlemail.com"},{"name":"stagas","email":"gstagas@gmail.com"},{"name":"amasad","email":"amjad.masad@gmail.com"},{"name":"juliangruber","email":"julian@juliangruber.com"},{"name":"shtylman","email":"shtylman@gmail.com"},{"name":"calvinfo","email":"calvin@calv.info"},{"name":"blakeembrey","email":"hello@blakeembrey.com"},{"name":"timoxley","email":"secoif@gmail.com"},{"name":"jonathanong","email":"jonathanrichardong@gmail.com"},{"name":"queckezz","email":"fabian.eichenberger@gmail.com"}],"directories":{}},"1.1.1":{"name":"component-builder","description":"builder for component","version":"1.1.1","author":{"name":"Jonathan Ong","email":"me@jongleberry.com","url":"http://jongleberry.com"},"license":"MIT","repository":{"type":"git","url":"component/builder2.js"},"dependencies":{"debug":"*","generator-supported":"~0.0.1","component-flatten":"^1.0.0","component-manifest":"^1.0.0","component-require2":"^1.0.0","css-url-rewriter":"~0.0.1","syntax-error":"^1.1.0","requires":"^1.0.0","graceful-fs":"^2.0.1","mkdirp":"~0.3.5","cp":"~0.1.1","chanel":"^2.0.0","co":"^3.0.2"},"devDependencies":{"component-resolver":"^1.0.0","builder-es6-module-to-cjs":"^1.0.0","rimraf":"^2.2.6","mocha":"^1.17.0","should":"^3.0.0","gnode":"0","regenerator":"0"},"scripts":{"test":"NODE=gnode make test","prepublish":"make clean build"},"_id":"component-builder@1.1.1","dist":{"shasum":"5b0881d5c7eb2143bfc5fd65d8afc6720ca42a0c","tarball":"http://registry.npmjs.org/component-builder/-/component-builder-1.1.1.tgz"},"_from":".","_npmVersion":"1.4.6","_npmUser":{"name":"jongleberry","email":"jonathanrichardong@gmail.com"},"maintainers":[{"name":"tjholowaychuk","email":"tj@vision-media.ca"},{"name":"jongleberry","email":"jonathanrichardong@gmail.com"},{"name":"dominicbarnes","email":"dominic@dbarnes.info"},{"name":"tootallnate","email":"nathan@tootallnate.net"},{"name":"rauchg","email":"rauchg@gmail.com"},{"name":"retrofox","email":"rdsuarez@gmail.com"},{"name":"coreh","email":"thecoreh@gmail.com"},{"name":"forbeslindesay","email":"forbes@lindesay.co.uk"},{"name":"kelonye","email":"kelonyemitchel@gmail.com"},{"name":"mattmueller","email":"mattmuelle@gmail.com"},{"name":"yields","email":"yields@icloud.com"},{"name":"anthonyshort","email":"antshort@gmail.com"},{"name":"ianstormtaylor","email":"ian@ianstormtaylor.com"},{"name":"cristiandouce","email":"cristian@gravityonmars.com"},{"name":"swatinem","email":"arpad.borsos@googlemail.com"},{"name":"stagas","email":"gstagas@gmail.com"},{"name":"amasad","email":"amjad.masad@gmail.com"},{"name":"juliangruber","email":"julian@juliangruber.com"},{"name":"shtylman","email":"shtylman@gmail.com"},{"name":"calvinfo","email":"calvin@calv.info"},{"name":"blakeembrey","email":"hello@blakeembrey.com"},{"name":"timoxley","email":"secoif@gmail.com"},{"name":"jonathanong","email":"jonathanrichardong@gmail.com"},{"name":"queckezz","email":"fabian.eichenberger@gmail.com"}],"directories":{}},"1.1.2":{"name":"component-builder","description":"builder for component","version":"1.1.2","author":{"name":"Jonathan Ong","email":"me@jongleberry.com","url":"http://jongleberry.com"},"license":"MIT","repository":{"type":"git","url":"component/builder2.js"},"dependencies":{"debug":"*","generator-supported":"~0.0.1","component-flatten":"^1.0.0","component-manifest":"^1.0.0","component-require2":"^1.0.0","css-url-rewriter":"~0.0.1","syntax-error":"^1.1.0","requires":"^1.0.0","graceful-fs":"^2.0.1","mkdirp":"~0.3.5","cp":"~0.1.1","chanel":"^2.0.0","co":"^3.0.2"},"devDependencies":{"component-resolver":"^1.0.0","builder-es6-module-to-cjs":"^1.0.0","rimraf":"^2.2.6","mocha":"^1.17.0","should":"^3.0.0","gnode":"0","regenerator":"0"},"scripts":{"test":"NODE=gnode make test","prepublish":"make clean build"},"_id":"component-builder@1.1.2","dist":{"shasum":"5f693f081c117985dba5499b326eab1f6970cf8e","tarball":"http://registry.npmjs.org/component-builder/-/component-builder-1.1.2.tgz"},"_from":".","_npmVersion":"1.4.6","_npmUser":{"name":"jongleberry","email":"jonathanrichardong@gmail.com"},"maintainers":[{"name":"tjholowaychuk","email":"tj@vision-media.ca"},{"name":"jongleberry","email":"jonathanrichardong@gmail.com"},{"name":"dominicbarnes","email":"dominic@dbarnes.info"},{"name":"tootallnate","email":"nathan@tootallnate.net"},{"name":"rauchg","email":"rauchg@gmail.com"},{"name":"retrofox","email":"rdsuarez@gmail.com"},{"name":"coreh","email":"thecoreh@gmail.com"},{"name":"forbeslindesay","email":"forbes@lindesay.co.uk"},{"name":"kelonye","email":"kelonyemitchel@gmail.com"},{"name":"mattmueller","email":"mattmuelle@gmail.com"},{"name":"yields","email":"yields@icloud.com"},{"name":"anthonyshort","email":"antshort@gmail.com"},{"name":"ianstormtaylor","email":"ian@ianstormtaylor.com"},{"name":"cristiandouce","email":"cristian@gravityonmars.com"},{"name":"swatinem","email":"arpad.borsos@googlemail.com"},{"name":"stagas","email":"gstagas@gmail.com"},{"name":"amasad","email":"amjad.masad@gmail.com"},{"name":"juliangruber","email":"julian@juliangruber.com"},{"name":"shtylman","email":"shtylman@gmail.com"},{"name":"calvinfo","email":"calvin@calv.info"},{"name":"blakeembrey","email":"hello@blakeembrey.com"},{"name":"timoxley","email":"secoif@gmail.com"},{"name":"jonathanong","email":"jonathanrichardong@gmail.com"},{"name":"queckezz","email":"fabian.eichenberger@gmail.com"}],"directories":{}},"1.1.3":{"name":"component-builder","description":"builder for component","version":"1.1.3","author":{"name":"Jonathan Ong","email":"me@jongleberry.com","url":"http://jongleberry.com"},"license":"MIT","repository":{"type":"git","url":"component/builder2.js"},"dependencies":{"debug":"*","generator-supported":"~0.0.1","component-flatten":"^1.0.0","component-manifest":"^1.0.0","component-require2":"^1.0.0","css-url-rewriter":"~0.0.1","syntax-error":"^1.1.0","requires":"^1.0.0","graceful-fs":"^2.0.1","mkdirp":"~0.3.5","cp":"~0.1.1","chanel":"^2.0.0","co":"^3.0.2"},"devDependencies":{"component-resolver":"^1.0.0","builder-es6-module-to-cjs":"^1.0.0","rimraf":"^2.2.6","mocha":"^1.17.0","should":"^3.0.0","gnode":"0","regenerator":"0"},"scripts":{"test":"NODE=gnode make test","prepublish":"make clean build"},"_id":"component-builder@1.1.3","dist":{"shasum":"37838b3788709c9cf1840092223252ce65b6a858","tarball":"http://registry.npmjs.org/component-builder/-/component-builder-1.1.3.tgz"},"_from":".","_npmVersion":"1.4.6","_npmUser":{"name":"jongleberry","email":"jonathanrichardong@gmail.com"},"maintainers":[{"name":"tjholowaychuk","email":"tj@vision-media.ca"},{"name":"jongleberry","email":"jonathanrichardong@gmail.com"},{"name":"dominicbarnes","email":"dominic@dbarnes.info"},{"name":"tootallnate","email":"nathan@tootallnate.net"},{"name":"rauchg","email":"rauchg@gmail.com"},{"name":"retrofox","email":"rdsuarez@gmail.com"},{"name":"coreh","email":"thecoreh@gmail.com"},{"name":"forbeslindesay","email":"forbes@lindesay.co.uk"},{"name":"kelonye","email":"kelonyemitchel@gmail.com"},{"name":"mattmueller","email":"mattmuelle@gmail.com"},{"name":"yields","email":"yields@icloud.com"},{"name":"anthonyshort","email":"antshort@gmail.com"},{"name":"ianstormtaylor","email":"ian@ianstormtaylor.com"},{"name":"cristiandouce","email":"cristian@gravityonmars.com"},{"name":"swatinem","email":"arpad.borsos@googlemail.com"},{"name":"stagas","email":"gstagas@gmail.com"},{"name":"amasad","email":"amjad.masad@gmail.com"},{"name":"juliangruber","email":"julian@juliangruber.com"},{"name":"shtylman","email":"shtylman@gmail.com"},{"name":"calvinfo","email":"calvin@calv.info"},{"name":"blakeembrey","email":"hello@blakeembrey.com"},{"name":"timoxley","email":"secoif@gmail.com"},{"name":"jonathanong","email":"jonathanrichardong@gmail.com"},{"name":"queckezz","email":"fabian.eichenberger@gmail.com"},{"name":"nami-doc","email":"vendethiel@hotmail.fr"}],"directories":{}},"1.1.4":{"name":"component-builder","description":"builder for component","version":"1.1.4","author":{"name":"Jonathan Ong","email":"me@jongleberry.com","url":"http://jongleberry.com"},"license":"MIT","repository":{"type":"git","url":"component/builder2.js"},"dependencies":{"debug":"*","generator-supported":"~0.0.1","component-flatten":"^1.0.0","component-manifest":"^1.0.0","component-require2":"^1.0.0","css-url-rewriter":"~0.0.1","syntax-error":"^1.1.0","requires":"^1.0.0","graceful-fs":"^2.0.1","mkdirp":"~0.3.5","cp":"~0.1.1","chanel":"^2.0.0","co":"^3.0.2"},"devDependencies":{"component-resolver":"^1.0.0","builder-es6-module-to-cjs":"^1.0.0","rimraf":"^2.2.6","mocha":"^1.17.0","should":"^3.0.0","gnode":"0","regenerator":"0"},"scripts":{"test":"NODE=gnode make test","prepublish":"make clean build"},"_id":"component-builder@1.1.4","dist":{"shasum":"cf2d5ea45027dd10e4e6e5b65eb9a2d18decdded","tarball":"http://registry.npmjs.org/component-builder/-/component-builder-1.1.4.tgz"},"_from":".","_npmVersion":"1.4.6","_npmUser":{"name":"jongleberry","email":"jonathanrichardong@gmail.com"},"maintainers":[{"name":"tjholowaychuk","email":"tj@vision-media.ca"},{"name":"jongleberry","email":"jonathanrichardong@gmail.com"},{"name":"dominicbarnes","email":"dominic@dbarnes.info"},{"name":"tootallnate","email":"nathan@tootallnate.net"},{"name":"rauchg","email":"rauchg@gmail.com"},{"name":"retrofox","email":"rdsuarez@gmail.com"},{"name":"coreh","email":"thecoreh@gmail.com"},{"name":"forbeslindesay","email":"forbes@lindesay.co.uk"},{"name":"kelonye","email":"kelonyemitchel@gmail.com"},{"name":"mattmueller","email":"mattmuelle@gmail.com"},{"name":"yields","email":"yields@icloud.com"},{"name":"anthonyshort","email":"antshort@gmail.com"},{"name":"ianstormtaylor","email":"ian@ianstormtaylor.com"},{"name":"cristiandouce","email":"cristian@gravityonmars.com"},{"name":"swatinem","email":"arpad.borsos@googlemail.com"},{"name":"stagas","email":"gstagas@gmail.com"},{"name":"amasad","email":"amjad.masad@gmail.com"},{"name":"juliangruber","email":"julian@juliangruber.com"},{"name":"shtylman","email":"shtylman@gmail.com"},{"name":"calvinfo","email":"calvin@calv.info"},{"name":"blakeembrey","email":"hello@blakeembrey.com"},{"name":"timoxley","email":"secoif@gmail.com"},{"name":"jonathanong","email":"jonathanrichardong@gmail.com"},{"name":"queckezz","email":"fabian.eichenberger@gmail.com"},{"name":"nami-doc","email":"vendethiel@hotmail.fr"}],"directories":{}},"1.1.5":{"name":"component-builder","description":"builder for component","version":"1.1.5","author":{"name":"Jonathan Ong","email":"me@jongleberry.com","url":"http://jongleberry.com"},"license":"MIT","repository":{"type":"git","url":"component/builder2.js"},"dependencies":{"debug":"*","generator-supported":"~0.0.1","component-flatten":"^1.0.0","component-manifest":"^1.0.0","component-require2":"^1.0.0","css-url-rewriter":"~0.0.1","syntax-error":"^1.1.0","requires":"^1.0.0","graceful-fs":"^2.0.1","mkdirp":"~0.3.5","cp":"~0.1.1","chanel":"^2.0.0","co":"^3.0.2"},"devDependencies":{"component-resolver":"^1.0.0","builder-es6-module-to-cjs":"^1.0.0","rimraf":"^2.2.6","mocha":"^1.17.0","should":"^3.0.0","gnode":"0","regenerator":"0"},"scripts":{"test":"NODE=gnode make test","prepublish":"make clean build"},"_id":"component-builder@1.1.5","dist":{"shasum":"0494aa1c8e1219163437c0489562fbac2c46cb67","tarball":"http://registry.npmjs.org/component-builder/-/component-builder-1.1.5.tgz"},"_from":".","_npmVersion":"1.4.6","_npmUser":{"name":"jongleberry","email":"jonathanrichardong@gmail.com"},"maintainers":[{"name":"tjholowaychuk","email":"tj@vision-media.ca"},{"name":"jongleberry","email":"jonathanrichardong@gmail.com"},{"name":"dominicbarnes","email":"dominic@dbarnes.info"},{"name":"tootallnate","email":"nathan@tootallnate.net"},{"name":"rauchg","email":"rauchg@gmail.com"},{"name":"retrofox","email":"rdsuarez@gmail.com"},{"name":"coreh","email":"thecoreh@gmail.com"},{"name":"forbeslindesay","email":"forbes@lindesay.co.uk"},{"name":"kelonye","email":"kelonyemitchel@gmail.com"},{"name":"mattmueller","email":"mattmuelle@gmail.com"},{"name":"yields","email":"yields@icloud.com"},{"name":"anthonyshort","email":"antshort@gmail.com"},{"name":"ianstormtaylor","email":"ian@ianstormtaylor.com"},{"name":"cristiandouce","email":"cristian@gravityonmars.com"},{"name":"swatinem","email":"arpad.borsos@googlemail.com"},{"name":"stagas","email":"gstagas@gmail.com"},{"name":"amasad","email":"amjad.masad@gmail.com"},{"name":"juliangruber","email":"julian@juliangruber.com"},{"name":"shtylman","email":"shtylman@gmail.com"},{"name":"calvinfo","email":"calvin@calv.info"},{"name":"blakeembrey","email":"hello@blakeembrey.com"},{"name":"timoxley","email":"secoif@gmail.com"},{"name":"jonathanong","email":"jonathanrichardong@gmail.com"},{"name":"queckezz","email":"fabian.eichenberger@gmail.com"},{"name":"nami-doc","email":"vendethiel@hotmail.fr"}],"directories":{}},"1.1.6":{"name":"component-builder","description":"builder for component","version":"1.1.6","author":{"name":"Jonathan Ong","email":"me@jongleberry.com","url":"http://jongleberry.com"},"license":"MIT","repository":{"type":"git","url":"git://github.com/component/builder2.js"},"dependencies":{"debug":"*","generator-supported":"~0.0.1","component-flatten":"^1.0.0","component-manifest":"^1.0.0","component-require2":"^1.0.0","css-url-rewriter":"~0.0.1","syntax-error":"^1.1.0","requires":"^1.0.0","graceful-fs":"^2.0.1","mkdirp":"~0.3.5","cp":"~0.1.1","chanel":"^2.0.0","co":"^3.0.2"},"devDependencies":{"component-resolver":"^1.0.0","builder-es6-module-to-cjs":"^1.0.0","rimraf":"^2.2.6","mocha":"^1.17.0","should":"^3.0.0","gnode":"0","regenerator":"0.4.6"},"scripts":{"test":"NODE=gnode make test","prepublish":"make clean build"},"bugs":{"url":"https://github.com/component/builder2.js/issues"},"homepage":"https://github.com/component/builder2.js","_id":"component-builder@1.1.6","_shasum":"1a2ef67f617bd4af2672a57e0d5634f8a59b3d47","_from":".","_npmVersion":"1.4.9","_npmUser":{"name":"clintwood","email":"clint@anotherway.co.za"},"maintainers":[{"name":"tjholowaychuk","email":"tj@vision-media.ca"},{"name":"jongleberry","email":"jonathanrichardong@gmail.com"},{"name":"dominicbarnes","email":"dominic@dbarnes.info"},{"name":"tootallnate","email":"nathan@tootallnate.net"},{"name":"rauchg","email":"rauchg@gmail.com"},{"name":"retrofox","email":"rdsuarez@gmail.com"},{"name":"coreh","email":"thecoreh@gmail.com"},{"name":"forbeslindesay","email":"forbes@lindesay.co.uk"},{"name":"kelonye","email":"kelonyemitchel@gmail.com"},{"name":"mattmueller","email":"mattmuelle@gmail.com"},{"name":"yields","email":"yields@icloud.com"},{"name":"anthonyshort","email":"antshort@gmail.com"},{"name":"ianstormtaylor","email":"ian@ianstormtaylor.com"},{"name":"cristiandouce","email":"cristian@gravityonmars.com"},{"name":"swatinem","email":"arpad.borsos@googlemail.com"},{"name":"stagas","email":"gstagas@gmail.com"},{"name":"amasad","email":"amjad.masad@gmail.com"},{"name":"juliangruber","email":"julian@juliangruber.com"},{"name":"shtylman","email":"shtylman@gmail.com"},{"name":"calvinfo","email":"calvin@calv.info"},{"name":"blakeembrey","email":"hello@blakeembrey.com"},{"name":"timoxley","email":"secoif@gmail.com"},{"name":"jonathanong","email":"jonathanrichardong@gmail.com"},{"name":"queckezz","email":"fabian.eichenberger@gmail.com"},{"name":"nami-doc","email":"vendethiel@hotmail.fr"},{"name":"clintwood","email":"clint@anotherway.co.za"}],"dist":{"shasum":"1a2ef67f617bd4af2672a57e0d5634f8a59b3d47","tarball":"http://registry.npmjs.org/component-builder/-/component-builder-1.1.6.tgz"},"directories":{}},"1.1.7":{"name":"component-builder","description":"builder for component","version":"1.1.7","author":{"name":"Jonathan Ong","email":"me@jongleberry.com","url":"http://jongleberry.com"},"license":"MIT","repository":{"type":"git","url":"git://github.com/component/builder2.js"},"dependencies":{"debug":"*","generator-supported":"~0.0.1","component-flatten":"^1.0.0","component-manifest":"^1.0.0","component-require2":"^1.0.0","css-url-rewriter":"~0.0.1","syntax-error":"^1.1.0","requires":"^1.0.0","graceful-fs":"^2.0.1","mkdirp":"~0.3.5","cp":"~0.1.1","chanel":"^2.0.0","co":"^3.0.2"},"devDependencies":{"component-resolver":"^1.0.0","builder-es6-module-to-cjs":"^1.0.0","rimraf":"^2.2.6","mocha":"^1.17.0","should":"^3.0.0","gnode":"0","regenerator":"0.4.6"},"scripts":{"test":"NODE=gnode make test","prepublish":"make clean build"},"bugs":{"url":"https://github.com/component/builder2.js/issues"},"homepage":"https://github.com/component/builder2.js","_id":"component-builder@1.1.7","_shasum":"048550b41705c249a4f4867c1e8d90641231fefb","_from":".","_npmVersion":"1.4.9","_npmUser":{"name":"clintwood","email":"clint@anotherway.co.za"},"maintainers":[{"name":"tjholowaychuk","email":"tj@vision-media.ca"},{"name":"jongleberry","email":"jonathanrichardong@gmail.com"},{"name":"dominicbarnes","email":"dominic@dbarnes.info"},{"name":"tootallnate","email":"nathan@tootallnate.net"},{"name":"rauchg","email":"rauchg@gmail.com"},{"name":"retrofox","email":"rdsuarez@gmail.com"},{"name":"coreh","email":"thecoreh@gmail.com"},{"name":"forbeslindesay","email":"forbes@lindesay.co.uk"},{"name":"kelonye","email":"kelonyemitchel@gmail.com"},{"name":"mattmueller","email":"mattmuelle@gmail.com"},{"name":"yields","email":"yields@icloud.com"},{"name":"anthonyshort","email":"antshort@gmail.com"},{"name":"ianstormtaylor","email":"ian@ianstormtaylor.com"},{"name":"cristiandouce","email":"cristian@gravityonmars.com"},{"name":"swatinem","email":"arpad.borsos@googlemail.com"},{"name":"stagas","email":"gstagas@gmail.com"},{"name":"amasad","email":"amjad.masad@gmail.com"},{"name":"juliangruber","email":"julian@juliangruber.com"},{"name":"shtylman","email":"shtylman@gmail.com"},{"name":"calvinfo","email":"calvin@calv.info"},{"name":"blakeembrey","email":"hello@blakeembrey.com"},{"name":"timoxley","email":"secoif@gmail.com"},{"name":"jonathanong","email":"jonathanrichardong@gmail.com"},{"name":"queckezz","email":"fabian.eichenberger@gmail.com"},{"name":"nami-doc","email":"vendethiel@hotmail.fr"},{"name":"clintwood","email":"clint@anotherway.co.za"},{"name":"thehydroimpulse","email":"dnfagnan@gmail.com"},{"name":"stephenmathieson","email":"me@stephenmathieson.com"},{"name":"trevorgerhardt","email":"trevorgerhardt@gmail.com"}],"dist":{"shasum":"048550b41705c249a4f4867c1e8d90641231fefb","tarball":"http://registry.npmjs.org/component-builder/-/component-builder-1.1.7.tgz"},"directories":{}},"1.1.8":{"name":"component-builder","description":"builder for component","version":"1.1.8","author":{"name":"Jonathan Ong","email":"me@jongleberry.com","url":"http://jongleberry.com"},"license":"MIT","repository":{"type":"git","url":"git://github.com/component/builder2.js"},"dependencies":{"debug":"*","generator-supported":"~0.0.1","component-flatten":"^1.0.0","component-manifest":"^1.0.0","component-require2":"^1.0.0","css-url-rewriter":"~0.0.1","syntax-error":"^1.1.1","requires":"^1.0.0","graceful-fs":"^2.0.1","mkdirp":"~0.3.5","cp":"~0.1.1","chanel":"^2.0.0","co":"^3.0.2"},"devDependencies":{"component-resolver":"^1.0.0","builder-es6-module-to-cjs":"^1.0.0","rimraf":"^2.2.6","mocha":"^1.17.0","should":"^3.0.0","gnode":"0","regenerator":"0.4.6"},"scripts":{"test":"NODE=gnode make test","prepublish":"make clean build"},"bugs":{"url":"https://github.com/component/builder2.js/issues"},"homepage":"https://github.com/component/builder2.js","_id":"component-builder@1.1.8","_shasum":"52828c5fdfc8b85bf20342d2e162aa431c65e112","_from":".","_npmVersion":"1.4.9","_npmUser":{"name":"clintwood","email":"clint@anotherway.co.za"},"maintainers":[{"name":"tjholowaychuk","email":"tj@vision-media.ca"},{"name":"jongleberry","email":"jonathanrichardong@gmail.com"},{"name":"dominicbarnes","email":"dominic@dbarnes.info"},{"name":"tootallnate","email":"nathan@tootallnate.net"},{"name":"rauchg","email":"rauchg@gmail.com"},{"name":"retrofox","email":"rdsuarez@gmail.com"},{"name":"coreh","email":"thecoreh@gmail.com"},{"name":"forbeslindesay","email":"forbes@lindesay.co.uk"},{"name":"kelonye","email":"kelonyemitchel@gmail.com"},{"name":"mattmueller","email":"mattmuelle@gmail.com"},{"name":"yields","email":"yields@icloud.com"},{"name":"anthonyshort","email":"antshort@gmail.com"},{"name":"ianstormtaylor","email":"ian@ianstormtaylor.com"},{"name":"cristiandouce","email":"cristian@gravityonmars.com"},{"name":"swatinem","email":"arpad.borsos@googlemail.com"},{"name":"stagas","email":"gstagas@gmail.com"},{"name":"amasad","email":"amjad.masad@gmail.com"},{"name":"juliangruber","email":"julian@juliangruber.com"},{"name":"shtylman","email":"shtylman@gmail.com"},{"name":"calvinfo","email":"calvin@calv.info"},{"name":"blakeembrey","email":"hello@blakeembrey.com"},{"name":"timoxley","email":"secoif@gmail.com"},{"name":"jonathanong","email":"jonathanrichardong@gmail.com"},{"name":"queckezz","email":"fabian.eichenberger@gmail.com"},{"name":"nami-doc","email":"vendethiel@hotmail.fr"},{"name":"clintwood","email":"clint@anotherway.co.za"},{"name":"thehydroimpulse","email":"dnfagnan@gmail.com"},{"name":"stephenmathieson","email":"me@stephenmathieson.com"},{"name":"trevorgerhardt","email":"trevorgerhardt@gmail.com"}],"dist":{"shasum":"52828c5fdfc8b85bf20342d2e162aa431c65e112","tarball":"http://registry.npmjs.org/component-builder/-/component-builder-1.1.8.tgz"},"directories":{}},"1.1.9":{"name":"component-builder","description":"builder for component","version":"1.1.9","author":{"name":"Jonathan Ong","email":"me@jongleberry.com","url":"http://jongleberry.com"},"license":"MIT","repository":{"type":"git","url":"git://github.com/component/builder2.js"},"dependencies":{"chanel":"^2.0.0","co":"^3.0.2","component-flatten":"^1.0.0","component-manifest":"^1.0.0","component-require2":"^1.0.0","cp":"~0.1.1","css-url-rewriter":"^0.1.0","debug":"*","generator-supported":"~0.0.1","graceful-fs":"^2.0.1","mkdirp":"~0.3.5","requires":"^1.0.0","syntax-error":"^1.1.1"},"devDependencies":{"component-resolver":"^1.0.0","builder-es6-module-to-cjs":"^1.0.0","rimraf":"^2.2.6","mocha":"^1.17.0","should":"^3.0.0","gnode":"0","regenerator":"0.4.6"},"scripts":{"test":"NODE=gnode make test","prepublish":"make clean build"},"gitHead":"483a5129f5496dd9c7ba482e3f41c5f69ee743d7","bugs":{"url":"https://github.com/component/builder2.js/issues"},"homepage":"https://github.com/component/builder2.js","_id":"component-builder@1.1.9","_shasum":"eddfa0ad11e11ff5296e907735d70227b60befb3","_from":".","_npmVersion":"1.4.14","_npmUser":{"name":"dominicbarnes","email":"dominic@dbarnes.info"},"maintainers":[{"name":"tjholowaychuk","email":"tj@vision-media.ca"},{"name":"jongleberry","email":"jonathanrichardong@gmail.com"},{"name":"dominicbarnes","email":"dominic@dbarnes.info"},{"name":"tootallnate","email":"nathan@tootallnate.net"},{"name":"rauchg","email":"rauchg@gmail.com"},{"name":"retrofox","email":"rdsuarez@gmail.com"},{"name":"coreh","email":"thecoreh@gmail.com"},{"name":"forbeslindesay","email":"forbes@lindesay.co.uk"},{"name":"kelonye","email":"kelonyemitchel@gmail.com"},{"name":"mattmueller","email":"mattmuelle@gmail.com"},{"name":"yields","email":"yields@icloud.com"},{"name":"anthonyshort","email":"antshort@gmail.com"},{"name":"ianstormtaylor","email":"ian@ianstormtaylor.com"},{"name":"cristiandouce","email":"cristian@gravityonmars.com"},{"name":"swatinem","email":"arpad.borsos@googlemail.com"},{"name":"stagas","email":"gstagas@gmail.com"},{"name":"amasad","email":"amjad.masad@gmail.com"},{"name":"juliangruber","email":"julian@juliangruber.com"},{"name":"shtylman","email":"shtylman@gmail.com"},{"name":"calvinfo","email":"calvin@calv.info"},{"name":"blakeembrey","email":"hello@blakeembrey.com"},{"name":"timoxley","email":"secoif@gmail.com"},{"name":"jonathanong","email":"jonathanrichardong@gmail.com"},{"name":"queckezz","email":"fabian.eichenberger@gmail.com"},{"name":"nami-doc","email":"vendethiel@hotmail.fr"},{"name":"clintwood","email":"clint@anotherway.co.za"},{"name":"thehydroimpulse","email":"dnfagnan@gmail.com"},{"name":"stephenmathieson","email":"me@stephenmathieson.com"},{"name":"trevorgerhardt","email":"trevorgerhardt@gmail.com"}],"dist":{"shasum":"eddfa0ad11e11ff5296e907735d70227b60befb3","tarball":"http://registry.npmjs.org/component-builder/-/component-builder-1.1.9.tgz"},"directories":{}}},"readme":"# component-builder2 [![Build Status](https://travis-ci.org/component/builder2.js.png)](https://travis-ci.org/component/builder2.js)\n\nAnother version of component's builder. Some differences:\n\n- Everything is streaming!\n- Split into multiple builders\n- Much leaner `require` implementation\n- Handles newer features like globs\n- Fixes a lot of issues with the previous builder\n\nDepends on:\n\n- [resolver](https://github.com/component/resolver.js) - resolved dependency tree\n- [flatten](https://github.com/jonathanong/flatten.js) - flatten the dependency tree to create a build order\n- [require2](https://github.com/component/require2) - this builder's `require()` implementation.\n- [manifest](https://github.com/component/manifest.js) - unglobs components' fields and creates `file` objects suitable for plugins\n- [builder-es6-module-to-cjs](https://github.com/component/builder-es6-module-to-cjs) - the included ES6 -> CJS plugin\n\nYou may be interested in:\n\n- [bundler](https://github.com/component/bundler.js) - create multiple bundles from the resolved dependency tree\n\n## Installation\n\n    npm install --save-dev component-builder\n    \n_NOTE_: Don't use the npm repo ~~[component-builder2](https://www.npmjs.org/package/component-builder2)~~ anymore. You get both versions [component/builder.js](https://github.com/component/builder.js) and [component/builder2.js](https://github.com/component/builder2.js) at this npm repo now: [component-builder](https://www.npmjs.org/package/component-builder)\n\n## Example\n\n```js\nvar fs = require('fs');\nvar resolve = require('component-resolver');\nvar build = require('component-builder');\n\n// resolve the dependency tree\nresolve(process.cwd(), {\n  // install the remote components locally\n  install: true\n}, function (err, tree) {\n  if (err) throw err;\n\n  // only include `.js` files from components' `.scripts` field\n  build.scripts(tree)\n    .use('scripts', build.plugins.js())\n    .end(function (err, string) {\n      if (err) throw err;\n      fs.writeFileSync('build.js', string);\n    });\n\n  // only include `.css` files from components' `.styles` field\n  build.styles(tree)\n    .use('styles', build.plugins.css())\n    .end(function (err, string) {\n      if (err) throw err;\n      fs.writeFileSync('build.css', string);\n    });\n\n  // only copy `images` to the build folder\n  build.files(tree)\n    .use('images', build.plugins.symlink())\n    .end(); // callback optional\n})\n```\n\n## Builders\n\nThere are three types of builders:\n\n- [`scripts`](https://github.com/component/builder2.js/blob/master/docs/scripts.md) - streaming builder for the `Javascript` file.\n- [`styles`](https://github.com/component/builder2.js/blob/master/docs/styles.md) - streaming builder for the `CSS` file.\n- [`files`](https://github.com/component/builder2.js/blob/master/docs/files.md) - channel-based builder for everything else, which generally means copying or symlinking\n\nYou'll also want to read docs on [`builder`](https://github.com/component/builder2.js/blob/master/docs/builders.md), which all three builders above inherit from.\n\nSee the documentation for more information on each.\n\n## License\n\nThe MIT License (MIT)\n\nCopyright (c) 2014 Jonathan Ong me@jongleberry.com\n\nPermission is hereby granted, free of charge, to any person obtaining a copy\nof this software and associated documentation files (the \"Software\"), to deal\nin the Software without restriction, including without limitation the rights\nto use, copy, modify, merge, publish, distribute, sublicense, and/or sell\ncopies of the Software, and to permit persons to whom the Software is\nfurnished to do so, subject to the following conditions:\n\nThe above copyright notice and this permission notice shall be included in\nall copies or substantial portions of the Software.\n\nTHE SOFTWARE IS PROVIDED \"AS IS\", WITHOUT WARRANTY OF ANY KIND, EXPRESS OR\nIMPLIED, INCLUDING BUT NOT LIMITED TO THE WARRANTIES OF MERCHANTABILITY,\nFITNESS FOR A PARTICULAR PURPOSE AND NONINFRINGEMENT. IN NO EVENT SHALL THE\nAUTHORS OR COPYRIGHT HOLDERS BE LIABLE FOR ANY CLAIM, DAMAGES OR OTHER\nLIABILITY, WHETHER IN AN ACTION OF CONTRACT, TORT OR OTHERWISE, ARISING FROM,\nOUT OF OR IN CONNECTION WITH THE SOFTWARE OR THE USE OR OTHER DEALINGS IN\nTHE SOFTWARE.\n","maintainers":[{"name":"tjholowaychuk","email":"tj@vision-media.ca"},{"name":"jongleberry","email":"jonathanrichardong@gmail.com"},{"name":"dominicbarnes","email":"dominic@dbarnes.info"},{"name":"tootallnate","email":"nathan@tootallnate.net"},{"name":"rauchg","email":"rauchg@gmail.com"},{"name":"retrofox","email":"rdsuarez@gmail.com"},{"name":"coreh","email":"thecoreh@gmail.com"},{"name":"forbeslindesay","email":"forbes@lindesay.co.uk"},{"name":"kelonye","email":"kelonyemitchel@gmail.com"},{"name":"mattmueller","email":"mattmuelle@gmail.com"},{"name":"yields","email":"yields@icloud.com"},{"name":"anthonyshort","email":"antshort@gmail.com"},{"name":"ianstormtaylor","email":"ian@ianstormtaylor.com"},{"name":"cristiandouce","email":"cristian@gravityonmars.com"},{"name":"swatinem","email":"arpad.borsos@googlemail.com"},{"name":"stagas","email":"gstagas@gmail.com"},{"name":"amasad","email":"amjad.masad@gmail.com"},{"name":"juliangruber","email":"julian@juliangruber.com"},{"name":"shtylman","email":"shtylman@gmail.com"},{"name":"calvinfo","email":"calvin@calv.info"},{"name":"blakeembrey","email":"hello@blakeembrey.com"},{"name":"timoxley","email":"secoif@gmail.com"},{"name":"jonathanong","email":"jonathanrichardong@gmail.com"},{"name":"queckezz","email":"fabian.eichenberger@gmail.com"},{"name":"nami-doc","email":"vendethiel@hotmail.fr"},{"name":"clintwood","email":"clint@anotherway.co.za"},{"name":"thehydroimpulse","email":"dnfagnan@gmail.com"},{"name":"stephenmathieson","email":"me@stephenmathieson.com"},{"name":"trevorgerhardt","email":"trevorgerhardt@gmail.com"},{"name":"timaschew","email":"timaschew@gmail.com"}],"time":{"modified":"2014-08-07T19:39:27.557Z","created":"2012-08-16T18:25:16.900Z","0.0.1":"2012-08-16T18:25:18.458Z","0.0.2":"2012-09-01T21:23:51.168Z","0.0.3":"2012-09-06T02:28:53.602Z","0.0.4":"2012-09-06T03:43:15.491Z","0.0.5":"2012-09-14T23:42:41.178Z","0.0.6":"2012-10-12T16:24:41.497Z","0.0.7":"2012-10-16T15:43:00.315Z","0.1.0":"2012-10-19T22:40:20.332Z","0.2.0":"2012-10-22T22:07:33.036Z","0.2.1":"2012-10-24T16:22:46.176Z","0.3.0":"2012-10-31T21:49:37.660Z","0.4.0":"2012-11-04T20:20:01.887Z","0.4.1":"2012-11-07T00:09:10.228Z","0.4.2":"2012-11-07T01:15:14.630Z","0.5.0":"2012-12-04T22:26:59.268Z","0.5.1":"2012-12-05T00:18:13.081Z","0.5.2":"2012-12-20T19:38:54.476Z","0.5.3":"2012-12-20T20:29:32.812Z","0.5.5":"2012-12-30T18:05:41.662Z","0.6.0":"2013-01-01T23:21:10.950Z","0.6.1":"2013-01-02T22:06:07.055Z","0.6.2":"2013-01-05T03:50:14.020Z","0.6.3":"2013-02-15T16:39:00.947Z","0.6.4":"2013-03-19T19:32:44.181Z","0.6.5":"2013-03-29T15:24:45.205Z","0.7.0":"2013-04-11T22:33:42.845Z","0.7.1":"2013-04-24T15:29:29.695Z","0.8.0":"2013-04-25T02:37:20.185Z","0.8.1":"2013-04-26T15:48:08.913Z","0.8.2":"2013-05-14T00:05:38.925Z","0.8.3":"2013-06-06T19:46:44.525Z","0.9.0":"2013-07-19T16:23:57.636Z","0.9.1":"2013-09-06T15:29:40.861Z","0.9.2":"2013-09-12T14:23:00.129Z","0.10.0":"2013-10-17T18:47:32.882Z","0.11.0":"2013-12-29T21:44:41.159Z","0.11.1":"2013-12-30T18:30:00.106Z","0.11.2":"2013-12-30T19:58:08.420Z","0.10.1":"2014-01-16T19:24:58.629Z","0.12.0":"2014-01-27T16:18:04.262Z","1.0.0":"2014-04-02T01:32:40.737Z","1.0.1":"2014-04-02T02:18:54.819Z","1.0.2":"2014-04-02T05:34:46.012Z","1.0.3":"2014-04-02T05:53:06.762Z","1.0.4":"2014-04-05T00:05:45.904Z","1.1.0":"2014-04-05T22:30:35.116Z","1.1.1":"2014-04-06T23:26:48.918Z","1.1.2":"2014-04-07T10:12:56.674Z","1.1.3":"2014-04-17T19:58:26.718Z","1.1.4":"2014-04-20T20:59:23.598Z","1.1.5":"2014-04-22T08:26:21.427Z","1.1.6":"2014-05-29T19:34:30.241Z","1.1.7":"2014-06-18T10:24:17.727Z","1.1.8":"2014-07-16T12:13:46.247Z","1.1.9":"2014-07-17T20:12:26.490Z"},"author":{"name":"Jonathan Ong","email":"me@jongleberry.com","url":"http://jongleberry.com"},"users":{"buritica":true},"repository":{"type":"git","url":"git://github.com/component/builder2.js"},"readmeFilename":"README.md","license":"MIT","homepage":"https://github.com/component/builder2.js","bugs":{"url":"https://github.com/component/builder2.js/issues"},"_attachments":{},"_etag":"\"9ZJ7CA0V1USWWGCSL6B4WRD6Q\""}